{
    "请求头": "User-Agent$MOBILE_UA",
    "主页url": "https://hifiri.com/forum-4.htm",
    "简介": "<p></p><h5>&&</p><h5>",
    "数组": "media-body\">&&</div>[不包含:使用说明与金币获取教程]",
    "图片": "https://p3-pc-sign.douyinpic.com/obj/tos-cn-i-0813/ocHBBC8E5QAfFAJ6Df6QLbAj8ADEmEnAKIF7Ae?from=876277922&x-expires=2013843600&x-signature=y8DcE5NxYzmwwe0FkMru%2BGoRQkg%3D",
    "标题": "\">&&</a>",
    "直接播放": "1",
    "链接": "href=\"&&\"",
    "链接前缀": "https://www.hifiii.com/",
    "播放链接": "href=\"&&\"",
    "跳转播放链接": "var ap4 = new APlayer*url:'&&'",
    "嗅探词": "index.m3u8#.m3u8#.mp4#.mp3#.m4a#.m4a?#.mp3?",
    "分类": "华语$1#日韩$2#欧美$3#Remix$4#纯音乐$5",
    "分类url": "https://www.hifiii.com/forum-{cateId}-{catePg}.htm?orderby=lastpid&follow=0"
}